pygismeteo_base/__init__.py
pygismeteo_base/_enum.py
pygismeteo_base/http.py
pygismeteo_base/py.typed
pygismeteo_base/responses.py
pygismeteo_base/types.py
pygismeteo_base/endpoints/__init__.py
pygismeteo_base/endpoints/_base.py
pygismeteo_base/endpoints/current.py
pygismeteo_base/endpoints/search.py
pygismeteo_base/endpoints/step24.py
pygismeteo_base/endpoints/step3.py
pygismeteo_base/endpoints/step6.py
pygismeteo_base/models/__init__.py
pygismeteo_base/models/_base.py
pygismeteo_base/models/current.py
pygismeteo_base/models/enums.py
pygismeteo_base/models/search_by_coordinates.py
pygismeteo_base/models/search_by_ip.py
pygismeteo_base/models/search_by_query.py
pygismeteo_base/models/step24.py
pygismeteo_base/models/step3.py
pygismeteo_base/models/step6.py
pygismeteo_base-6.0.2.dist-info/METADATA
pygismeteo_base-6.0.2.dist-info/WHEEL
pygismeteo_base-6.0.2.dist-info/licenses/LICENSE
pygismeteo_base-6.0.2.dist-info/RECORD
