Metadata-Version: 2.4
Name: pygismeteo-base
Version: 6.0.2
Summary: Internal library for pygismeteo and aiopygismeteo
Project-URL: repository, https://github.com/monosans/pygismeteo-base
Author-email: monosans <hsyqixco@protonmail.com>
License-Expression: MIT
License-File: LICENSE
Classifier: Framework :: Pydantic
Classifier: Framework :: Pydantic :: 2
Classifier: Natural Language :: Russian
Classifier: Operating System :: OS Independent
Classifier: Programming Language :: Python
Classifier: Programming Language :: Python :: 3 :: Only
Classifier: Programming Language :: Python :: 3.9
Classifier: Programming Language :: Python :: 3.10
Classifier: Programming Language :: Python :: 3.11
Classifier: Programming Language :: Python :: 3.12
Classifier: Programming Language :: Python :: 3.13
Classifier: Programming Language :: Python :: 3.14
Classifier: Programming Language :: Python :: 3.15
Classifier: Typing :: Typed
Requires-Python: >=3.9
Requires-Dist: pydantic>=2
Requires-Dist: typing-extensions>=4.4
